typesentry/__init__.py
typesentry/__version__.py
typesentry/checks.py
typesentry/config.py
typesentry/signature.py
typesentry-0.2.6.dist-info/LICENSE.txt
typesentry-0.2.6.dist-info/METADATA
typesentry-0.2.6.dist-info/RECORD
typesentry-0.2.6.dist-info/WHEEL
typesentry-0.2.6.dist-info/top_level.txt
typesentry-0.2.6.dist-info/zip-safe
